Metadata-Version: 2.1
Name: naislinter
Version: 1.0.2
Summary: Lints naiserator.yaml files
Home-page: https://github.com/chinatsu/naislinter
Author: Kent Daleng
Author-email: kent.stefan.daleng@nav.no
License: MIT
Platform: UNKNOWN
